sadrec/__init__.py
sadrec/gui.py
sadrec/main.py
sadrec/recorder.py
sadrec/spike_detection.py
sadrec/utils.py
sadrec-0.2.0.dist-info/METADATA
sadrec-0.2.0.dist-info/WHEEL
sadrec-0.2.0.dist-info/entry_points.txt
sadrec-0.2.0.dist-info/top_level.txt
sadrec-0.2.0.dist-info/RECORD
