Metadata-Version: 2.4
Name: sadrec
Version: 0.2.0
Summary: Light-weight electrophysiology audio recorder with live plotting and spike detection
Author-email: Nils <you@example.com>
License-Expression: MIT
Project-URL: Source, https://github.com/UniNilsBrehm/sadrec
Project-URL: Docs, https://github.com/UniNilsBrehm/sadrec#readme
Requires-Python: >=3.9
Requires-Dist: numpy
Requires-Dist: scipy
Requires-Dist: pyqtgraph
Requires-Dist: PyQt6
Requires-Dist: pyaudio
Requires-Dist: soundfile
